python_package/__init__.py
python_package/hello_world.py
foo_bar_eggs_baruch-0.0.2.dist-info/LICENSE
foo_bar_eggs_baruch-0.0.2.dist-info/WHEEL
foo_bar_eggs_baruch-0.0.2.dist-info/METADATA
foo_bar_eggs_baruch-0.0.2.dist-info/RECORD
